convert_aram/__init__.py
convert_aram/admin.py
convert_aram/apps.py
convert_aram/models.py
convert_aram/urls.py
convert_aram/views.py
convert_aram/migrations/__init__.py
convert_aran-0.1.4.dist-info/licenses/LICENCE
convert_aran-0.1.4.dist-info/METADATA
convert_aran-0.1.4.dist-info/WHEEL
convert_aran-0.1.4.dist-info/top_level.txt
convert_aran-0.1.4.dist-info/RECORD
